<?xml version="1.0" encoding="utf-8"?>
<Resources Culture="it-IT">
	<Group Type="String">
		<Items>
			<Item Name="Caption" Value="Destinatario del servizio" />
			<Item Name="Columns.Account.Caption" Value="Account" />
			<Item Name="Columns.Contact.Caption" Value="Contatto" />
			<Item Name="Columns.Department.Caption" Value="Dipartimento" />
			<Item Name="Columns.ServicePact.Caption" Value="Contratto di servizio" />
			<Item Name="Columns.Type.Caption" Value="Tipo" />
		</Items>
	</Group>
</Resources>