<?xml version="1.0" encoding="utf-8"?>
<Resources Culture="nl-NL">
	<Group Type="String">
		<Items>
			<Item Name="Caption" Value="Basiscase" />
			<Item Name="Columns.Account.Caption" Value="Bedrijf" />
			<Item Name="Columns.Category.Caption" Value="Categorie" />
			<Item Name="Columns.ClosureCode.Caption" Value="Reden afsluiting" />
			<Item Name="Columns.ClosureDate.Caption" Value="Gesloten op" />
			<Item Name="Columns.Contact.Caption" Value="Contact" />
			<Item Name="Columns.FirstSolutionProvidedOn.Caption" Value="Eerste oplostijd" />
			<Item Name="Columns.Group.Caption" Value="Groep" />
			<Item Name="Columns.Notes.Caption" Value="Aantekeningen" />
			<Item Name="Columns.Number.Caption" Value="Nummer" />
			<Item Name="Columns.Origin.Caption" Value="Bron" />
			<Item Name="Columns.Owner.Caption" Value="Eigenaar" />
			<Item Name="Columns.Priority.Caption" Value="Prioriteit" />
			<Item Name="Columns.RegisteredOn.Caption" Value="Registratiedatum" />
			<Item Name="Columns.RespondedOn.Caption" Value="Werkelijke responstijd" />
			<Item Name="Columns.ResponseDate.Caption" Value="Responstijd" />
			<Item Name="Columns.ResponseOverdue.Caption" Value="Respons achterstand" />
			<Item Name="Columns.SatisfactionLevel.Caption" Value="Tevredenheidsniveau" />
			<Item Name="Columns.SatisfactionLevelComment.Caption" Value="Feedback Aantekeningen" />
			<Item Name="Columns.Solution.Caption" Value="Oplossing" />
			<Item Name="Columns.SolutionDate.Caption" Value="Oplostijd" />
			<Item Name="Columns.SolutionOverdue.Caption" Value="Achterstallige oplossing" />
			<Item Name="Columns.SolutionProvidedOn.Caption" Value="Werkelijke oplostijd" />
			<Item Name="Columns.SolutionRemains.Caption" Value="Resteert tot oplostijd" />
			<Item Name="Columns.Status.Caption" Value="Status" />
			<Item Name="Columns.Subject.Caption" Value="Onderwerp" />
			<Item Name="Columns.Symptoms.Caption" Value="Omschrijving" />
		</Items>
	</Group>
</Resources>