<?xml version="1.0" encoding="utf-8"?>
<Resources Culture="it-IT">
	<Group Type="String">
		<Items>
			<Item Name="Caption" Value="SatisfactionLevelLookupEditPage" />
			<Item Name="Images.e40ee1e7-e961-42e2-b040-d270601ef686.Caption" Value="DefaultImage" />
			<Item Name="LocalizableStrings.PointTipMessage.Caption" Value="PointTipMessage" />
			<Item Name="LocalizableStrings.PointTipMessage.Value" Value="Si prega di inserire un numero intero (1, 2, 3...). Il livello di soddisfazione non può essere zero." />
			<Item Name="LocalizableStrings.ShouldBeMoreThanZeroValidationMessage.Caption" Value="ShouldBeMoreThanZeroValidationMessage" />
			<Item Name="LocalizableStrings.ShouldBeMoreThanZeroValidationMessage.Value" Value="Deve essere maggiore di zero" />
		</Items>
	</Group>
</Resources>