<?xml version="1.0" encoding="utf-8"?>
<Resources Culture="th-TH">
	<Group Type="String">
		<Items>
			<Item Name="Caption" Value="โครงสร้างข้อมูลหน้าแก้ไขรายละเอียด - บริการในสัญญาการบริการ" />
			<Item Name="LocalizableStrings.CalendarCaption.Value" Value="ปฏิทิน" />
			<Item Name="LocalizableStrings.ReactionTimeDayTypeCaption.Value" Value="ประเภทวันเวลาการตอบสนอง" />
			<Item Name="LocalizableStrings.ReactionTimeUnitCaption.Value" Value="Response time unit" />
			<Item Name="LocalizableStrings.ReactionTimeValueCaption.Value" Value="เวลาตอบสนอง" />
			<Item Name="LocalizableStrings.ServiceItemCaption.Value" Value="บริการ" />
			<Item Name="LocalizableStrings.ServicePactCaption.Value" Value="สัญญาการบริการ" />
			<Item Name="LocalizableStrings.SolutionTimeDayTypeCaption.Value" Value="ประเภทของวันเวลาการแก้ปัญหา" />
			<Item Name="LocalizableStrings.SolutionTimeUnitCaption.Value" Value="Resolution time unit" />
			<Item Name="LocalizableStrings.SolutionTimeValueCaption.Value" Value="เวลาแก้ปัญหา" />
			<Item Name="LocalizableStrings.StatusCaption.Value" Value="สถานะ" />
		</Items>
	</Group>
</Resources>